{
    "mc": {
        "tw_dingshen": {
            "frameRate": 24,
            "labels": [
                {
                    "name": "1",
                    "frame": 1,
                    "end": 8
                }
            ],
            "events": [],
            "frames": [
                {
                    "res": "b##0001",
                    "x": -54,
                    "y": -70
                },
                {
                    "res": "b##0002",
                    "x": -55,
                    "y": -72
                },
                {
                    "res": "b##0003",
                    "x": -56,
                    "y": -73
                },
                {
                    "res": "b##0004",
                    "x": -57,
                    "y": -74
                },
                {
                    "res": "b##0005",
                    "x": -57,
                    "y": -75
                },
                {
                    "res": "b##0006",
                    "x": -57,
                    "y": -76
                },
                {
                    "res": "b##0007",
                    "x": -57,
                    "y": -70
                },
                {
                    "res": "b##0008",
                    "x": -53,
                    "y": -67
                }
            ]
        }
    },
    "res": {
        "b##0007": {
            "x": 132,
            "y": 97,
            "w": 125,
            "h": 88
        },
        "b##0008": {
            "x": 381,
            "y": 90,
            "w": 123,
            "h": 85
        },
        "b##0001": {
            "x": 381,
            "y": 1,
            "w": 127,
            "h": 87
        },
        "b##0002": {
            "x": 1,
            "y": 96,
            "w": 129,
            "h": 91
        },
        "b##0005": {
            "x": 259,
            "y": 1,
            "w": 120,
            "h": 93
        },
        "b##0003": {
            "x": 1,
            "y": 1,
            "w": 130,
            "h": 93
        },
        "b##0006": {
            "x": 133,
            "y": 1,
            "w": 124,
            "h": 94
        },
        "b##0004": {
            "x": 259,
            "y": 96,
            "w": 117,
            "h": 92
        }
    }
}